setup.py
pyldap_orm/__init__.py
pyldap_orm/controls.py
pyldap_orm/core.py
pyldap_orm/exceptions.py
pyldap_orm/models.py
pyldap_orm/session.py
pyldap_orm.egg-info/PKG-INFO
pyldap_orm.egg-info/SOURCES.txt
pyldap_orm.egg-info/dependency_links.txt
pyldap_orm.egg-info/not-zip-safe
pyldap_orm.egg-info/requires.txt
pyldap_orm.egg-info/top_level.txt