Metadata-Version: 1.0
Name: pyldap-orm
Version: 0.0.1
Summary: A simple LDAP ORM to make LDAP access using Python Objects
Home-page: http://github.com/asyd/pyldap_orm
Author: Bruno Bonfils
Author-email: bbonfils@gmail.com
License: Apache License 2.0
Platform: UNKNOWN
